<?xml version="1.0" encoding="utf-8" ?>
<dwsync>
<file name="APhoto.jpg" server="54.245.48.46//var/www/html/devElements/" local="131970590720000000" remote="131970535610000000" Dst="-1" />
<file name="Casey_Profile.jpg" server="54.245.48.46//var/www/html/devElements/" local="131970590720000000" remote="131970586720000000" Dst="-1" />
<file name="DJ profile.jpg" server="54.245.48.46//var/www/html/devElements/" local="131970590720000000" remote="131970535620000000" Dst="-1" />
<file name="Doran_Profile.JPG" server="54.245.48.46//var/www/html/devElements/" local="131970590720000000" remote="131970535620000000" Dst="-1" />
<file name="Droid_Slam.png" server="54.245.48.46//var/www/html/devElements/" local="131970590720000000" remote="131970535630000000" Dst="-1" />
<file name="Marie_Profile_2016-07-27.png" server="54.245.48.46//var/www/html/devElements/" local="131970590720000000" remote="131970535630000000" Dst="-1" />
<file name="portfolioSS.PNG" server="54.245.48.46//var/www/html/devElements/" local="131970535640000000" remote="131970535640000000" Dst="2" />
<file name="typeBitScreenShot.PNG" server="54.245.48.46//var/www/html/devElements/" local="131970535650000000" remote="131970535650000000" Dst="2" />
<file name="Doran_ProfileV2.png" server="54.245.48.46//var/www/html/devElements/" local="131970590720000000" remote="131970535620000000" Dst="-1" />
<file name="petConnectScreenShot.PNG" server="54.245.48.46//var/www/html/devElements/" local="131970535640000000" remote="131970535640000000" Dst="2" />
</dwsync>